[
  {
    "text": "Winter Projects will be held internally unless people are very keen to get involved",
    "time": "11/05/20"
  },
  {
    "text": "The fridge is no longer open to the public as being raided is a significant financial burden on the club",
    "time": "14/02/20"
  },
  {
    "text": "Vote Drew for president in upcoming election",
    "time": "01/02/20"
  },
  {
    "text": "Lorem ipsum dolor sit amet consectetur, adipisicing elit. Possimus tempore quia deserunt praesentium maiores optio blanditiis voluptas labore repellat, excepturi, quidem aliquid eum soluta unde ipsum repellendus molestias consectetur eligendi! Lorem ipsum dolor sit, amet consectetur adipisicing elit. Eius, reiciendis a adipisci sequi placeat porro eum laborum ipsum voluptatum excepturi aliquid cum, commodi rem ad repudiandae! Possimus, facilis minima",
    "time": "12/04/19"
  }
]
